aiida_aurora/__init__.py
aiida_aurora/cli.py
aiida_aurora/helpers.py
aiida_aurora/monitors.py
aiida_aurora/parsers.py
aiida_aurora/scheduler.py
aiida_aurora/calculations/__init__.py
aiida_aurora/calculations/cycler.py
aiida_aurora/calculations/fake.py
aiida_aurora/data/__init__.py
aiida_aurora/data/battery.py
aiida_aurora/data/control.py
aiida_aurora/data/experiment.py
aiida_aurora/schemas/__init__.py
aiida_aurora/schemas/battery.py
aiida_aurora/schemas/cycling.py
aiida_aurora/schemas/dgbowl/__init__.py
aiida_aurora/schemas/dgbowl/converters/__init__.py
aiida_aurora/schemas/dgbowl/converters/method.py
aiida_aurora/schemas/dgbowl/converters/sample.py
aiida_aurora/schemas/utils/__init__.py
aiida_aurora/utils/__init__.py
aiida_aurora/utils/analyzers.py
aiida_aurora/utils/cycling_analysis.py
aiida_aurora/utils/parsers.py
aiida_aurora/workflows/__init__.py
aiida_aurora/workflows/cycling_sequence.py
aiida_aurora-0.5.1.dist-info/entry_points.txt
aiida_aurora-0.5.1.dist-info/LICENSE
aiida_aurora-0.5.1.dist-info/WHEEL
aiida_aurora-0.5.1.dist-info/METADATA
aiida_aurora-0.5.1.dist-info/RECORD
