Metadata-Version: 2.1
Name: aiida-aurora
Version: 0.5.1
Summary: AiiDA plugin for the Aurora platform.
Keywords: aiida,plugin,aurora
Author-email: Loris Ercole <loris.ercole@gmail.com>, "Francisco F. Ramirez" <ramirezfranciscof@gmail.com>, Edan Bainglass <edan.bainglass@psi.ch>, Giovanni Pizzi <giovanni.pizzi@psi.ch>
Requires-Python: >=3.9
Classifier: Programming Language :: Python
Classifier: Intended Audience :: Science/Research
Classifier: License :: OSI Approved :: MIT License
Classifier: Natural Language :: English
Classifier: Development Status :: 3 - Alpha
Classifier: Framework :: AiiDA
Requires-Dist: aiida-core>=2.0,<3
Requires-Dist: aiida-ssh2win>=0.2
Requires-Dist: dgbowl-schemas>=116
Requires-Dist: scipy>=1.5.4,<2
Requires-Dist: pandas~=1.5
Requires-Dist: sphinx ; extra == "docs"
Requires-Dist: sphinx_rtd_theme ; extra == "docs"
Requires-Dist: sphinxcontrib-contentui ; extra == "docs"
Requires-Dist: sphinxcontrib-details-directive ; extra == "docs"
Requires-Dist: furo ; extra == "docs"
Requires-Dist: markupsafe<2.1 ; extra == "docs"
Requires-Dist: pre-commit~=2.2 ; extra == "pre-commit"
Requires-Dist: pgtest~=1.3.1 ; extra == "testing"
Requires-Dist: wheel~=0.31 ; extra == "testing"
Requires-Dist: coverage[toml] ; extra == "testing"
Requires-Dist: pytest~=6.0 ; extra == "testing"
Requires-Dist: pytest-cov ; extra == "testing"
Project-URL: Source, https://github.com/EmpaEconversion/aiida-aurora
Provides-Extra: docs
Provides-Extra: pre-commit
Provides-Extra: testing
